detalog/__init__.py
detalog/handlers.py
detalog-0.1.0.dist-info/LICENSE
detalog-0.1.0.dist-info/METADATA
detalog-0.1.0.dist-info/WHEEL
detalog-0.1.0.dist-info/RECORD
