Metadata-Version: 2.1
Name: detalog
Version: 0.1.0
Summary: Logger for awesome Deta Space applications based on awesome PingBack events aggregator
License: MIT
Author: mamsdeveloper
Author-email: butvin.mihail@yandex.ru
Requires-Python: >=3.9,<4.0
Classifier: License :: OSI Approved :: MIT License
Classifier: Programming Language :: Python :: 3
Classifier: Programming Language :: Python :: 3.9
Classifier: Programming Language :: Python :: 3.10
Classifier: Programming Language :: Python :: 3.11
Requires-Dist: requests (>=2.28.2,<3.0.0)
